package_1/__init__.py
package_1/__main__.py
package_1/arithmetic.py
package_1/plugins.py
package_2/__init__.py
package_2/__main__.py
python_project_templates-0.1.5.dist-info/entry_points.txt
python_project_templates-0.1.5.dist-info/LICENSE
python_project_templates-0.1.5.dist-info/WHEEL
python_project_templates-0.1.5.dist-info/METADATA
python_project_templates-0.1.5.dist-info/RECORD
